LICENSE.txt
LICENSE_SUPPLEMENTAL_DISCLAIMER.txt
MANIFEST.in
NOTICES.txt
README.rst
setup.cfg
setup.py
versioneer.py
altuscli/__init__.py
altuscli/_version.py
altuscli/altusrequest.py
altuscli/argparser.py
altuscli/argprocess.py
altuscli/arguments.py
altuscli/auth.py
altuscli/clicommand.py
altuscli/clidriver.py
altuscli/client.py
altuscli/compat.py
altuscli/completer.py
altuscli/configloader.py
altuscli/credentials.py
altuscli/docs.py
altuscli/endpoint.py
altuscli/exceptions.py
altuscli/formatter.py
altuscli/help.py
altuscli/loader.py
altuscli/main.py
altuscli/model.py
altuscli/paginate.py
altuscli/paramfile.py
altuscli/parser.py
altuscli/retryhandler.py
altuscli/schema.py
altuscli/serialize.py
altuscli/shorthand.py
altuscli/signers.py
altuscli/table.py
altuscli/text.py
altuscli/textwriter.py
altuscli/translate.py
altuscli/utils.py
altuscli/validate.py
altuscli.egg-info/PKG-INFO
altuscli.egg-info/SOURCES.txt
altuscli.egg-info/dependency_links.txt
altuscli.egg-info/entry_points.txt
altuscli.egg-info/requires.txt
altuscli.egg-info/top_level.txt
altuscli/data/_retry.json
altuscli/data/aliases.yaml
altuscli/data/cli.json
altuscli/data/arcusadmin/arcusadmin.yaml
altuscli/data/coreadmin/coreadmin.yaml
altuscli/data/dataeng/dataeng.yaml
altuscli/data/dataengadmin/dataengadmin.yaml
altuscli/data/dataware/dataware.yaml
altuscli/data/dbus/dbus.yaml
altuscli/data/environments/environments.yaml
altuscli/data/iam/iam.yaml
altuscli/data/navopt/navopt.yaml
altuscli/data/sdxadmin/sdxadmin.yaml
altuscli/data/sigmaadmin/sigmaadmin.yaml
altuscli/data/wa/wa.yaml
altuscli/doc/__init__.py
altuscli/doc/docstringparser.py
altuscli/doc/restdoc.py
altuscli/doc/style.py
altuscli/examples/configure/_description.rst
altuscli/examples/configure/get/_description.rst
altuscli/examples/configure/get/_examples.rst
altuscli/examples/configure/set/_description.rst
altuscli/examples/configure/set/_examples.rst
altuscli/examples/dataeng/submit-jobs.rst
altuscli/examples/ds/init/_description.rst
altuscli/examples/ds/init/_examples.rst
altuscli/examples/ds/restore/_description.rst
altuscli/examples/ds/restore/_examples.rst
altuscli/examples/ds/run/_description.rst
